gradoptorch/__init__.py
gradoptorch/gradoptorch.py
gradoptorch/lstorch.py
gradoptorch/module.py
gradoptorch-0.1.1.dist-info/LICENSE
gradoptorch-0.1.1.dist-info/METADATA
gradoptorch-0.1.1.dist-info/WHEEL
gradoptorch-0.1.1.dist-info/RECORD
