Metadata-Version: 2.1
Name: gradoptorch
Version: 0.1.1
Summary: Classical gradient based optimization in PyTorch
License: GNUv3
Author: Kevin Course
Author-email: kevin.course@mail.utoronto.ca
Requires-Python: >=3.10,<4.0
Classifier: License :: Other/Proprietary License
Classifier: Programming Language :: Python :: 3
Classifier: Programming Language :: Python :: 3.10
Classifier: Programming Language :: Python :: 3.11
Requires-Dist: jaxtyping (>=0.2.23,<0.3.0)
Requires-Dist: torch (>=2.1.0,<3.0.0)
